data_analysis_gui/__init__.py
data_analysis_gui/main.py
data_analysis_gui/main_window.py
data_analysis_gui/plot_manager.py
data_analysis_gui/config/__init__.py
data_analysis_gui/config/exceptions.py
data_analysis_gui/config/logging.py
data_analysis_gui/config/plot_style.py
data_analysis_gui/config/session_settings.py
data_analysis_gui/config/settings.py
data_analysis_gui/config/themes.py
data_analysis_gui/core/__init__.py
data_analysis_gui/core/analysis_engine.py
data_analysis_gui/core/analysis_plot.py
data_analysis_gui/core/app_controller.py
data_analysis_gui/core/data_extractor.py
data_analysis_gui/core/dataset.py
data_analysis_gui/core/iv_analysis.py
data_analysis_gui/core/metrics_calculator.py
data_analysis_gui/core/models.py
data_analysis_gui/core/params.py
data_analysis_gui/core/plot_formatter.py
data_analysis_gui/core/loaders/__init__.py
data_analysis_gui/core/loaders/abf_loader.py
data_analysis_gui/core/loaders/wcp_loader.py
data_analysis_gui/dialogs/__init__.py
data_analysis_gui/dialogs/analysis_plot_dialog.py
data_analysis_gui/dialogs/batch_dialog.py
data_analysis_gui/dialogs/batch_results_window.py
data_analysis_gui/dialogs/batch_sweep_extractor_dialog.py
data_analysis_gui/dialogs/bg_subtraction_dialog.py
data_analysis_gui/dialogs/current_density_dialog.py
data_analysis_gui/dialogs/current_density_results_window.py
data_analysis_gui/dialogs/extract_sweeps_dialog.py
data_analysis_gui/dialogs/leak_subtraction_dialog.py
data_analysis_gui/dialogs/ramp_iv_batch_sweep_dialog.py
data_analysis_gui/dialogs/ramp_iv_dialog.py
data_analysis_gui/dialogs/reject_sweeps_dialog.py
data_analysis_gui/gui_services/__init__.py
data_analysis_gui/gui_services/clipboard_service.py
data_analysis_gui/gui_services/file_dialog_service.py
data_analysis_gui/gui_services/main_range_coordinator.py
data_analysis_gui/gui_services/view_state_manager.py
data_analysis_gui/logo/logo.icns
data_analysis_gui/logo/logo.ico
data_analysis_gui/services/__init__.py
patchbatch-1.0.4.dist-info/licenses/LICENSE.md
patchbatch-1.0.4.dist-info/METADATA
patchbatch-1.0.4.dist-info/WHEEL
patchbatch-1.0.4.dist-info/entry_points.txt
patchbatch-1.0.4.dist-info/top_level.txt
patchbatch-1.0.4.dist-info/RECORD
