Metadata-Version: 2.4
Name: patchbatch
Version: 1.0.4
Summary: Batch analysis tool for patch-clamp electrophysiology data
Author-email: Charles Kissell <kissell.r@northeastern.edu>
License: MIT
Project-URL: Homepage, https://github.com/ck852/patchbatch
Project-URL: Repository, https://github.com/ck852/patchbatch
Project-URL: Documentation, https://github.com/ck852/patchbatch#readme
Project-URL: Issues, https://github.com/ck852/patchbatch/issues
Project-URL: Changelog, https://github.com/ck852/patchbatch/blob/main/CHANGELOG.md
Keywords: electrophysiology,patch-clamp,data-analysis
Classifier: Development Status :: 4 - Beta
Classifier: Intended Audience :: Science/Research
Classifier: Intended Audience :: Healthcare Industry
Classifier: License :: OSI Approved :: MIT License
Classifier: License :: OSI Approved :: GNU Lesser General Public License v3 (LGPLv3)
Classifier: Programming Language :: Python :: 3
Classifier: Programming Language :: Python :: 3.9
Classifier: Programming Language :: Python :: 3.10
Classifier: Programming Language :: Python :: 3.11
Classifier: Programming Language :: Python :: 3.12
Classifier: Topic :: Scientific/Engineering
Classifier: Topic :: Scientific/Engineering :: Medical Science Apps.
Classifier: Topic :: Scientific/Engineering :: Visualization
Classifier: Operating System :: OS Independent
Classifier: Environment :: X11 Applications :: Qt
Requires-Python: >=3.9
License-File: LICENSE.md
Requires-Dist: PySide6>=6.2.0
Requires-Dist: numpy>=1.20.0
Requires-Dist: scipy>=1.9.0
Requires-Dist: matplotlib>=3.6.0
Requires-Dist: pyabf>=2.3.0
Requires-Dist: pandas>=1.3.0
Provides-Extra: test
Requires-Dist: pytest; extra == "test"
Requires-Dist: pytest-xvfb; extra == "test"
Provides-Extra: dev
Requires-Dist: build; extra == "dev"
Requires-Dist: twine; extra == "dev"
Dynamic: license-file
